readdocx/__init__.py
ReadDocx-0.0.1.dist-info/LICENSE
ReadDocx-0.0.1.dist-info/METADATA
ReadDocx-0.0.1.dist-info/WHEEL
ReadDocx-0.0.1.dist-info/top_level.txt
ReadDocx-0.0.1.dist-info/RECORD
