Metadata-Version: 2.1
Name: ReadDocx
Version: 0.0.1
Summary: ReadDocx ——直接提取Word文档（不包含样式信息）
Home-page: https://github.com/CHUA-X/ReadDocx
Author: CHUA某人
Author-email: CHUA某人 <chua-x@outlook.com>
Project-URL: Homepage, https://github.com/CHUA-X/ReadDocx
Project-URL: Bug Tracker, https://github.com/CHUA-X/ReadDocx/issues
Classifier: Development Status :: 3 - Alpha
Classifier: Programming Language :: Python
Classifier: Programming Language :: Python :: 3
Classifier: Programming Language :: Python :: 3 :: Only
Classifier: License :: OSI Approved :: MIT License
Classifier: Natural Language :: Chinese (Simplified)
Classifier: Natural Language :: English
Classifier: Operating System :: Unix
Classifier: Operating System :: POSIX :: Linux
Classifier: Operating System :: MacOS :: MacOS X
Classifier: Operating System :: Microsoft :: Windows
Requires-Python: >=3.6
License-File: LICENSE
